odoo/addons/mgmtsystem_nonconformity_repair/README.rst
odoo/addons/mgmtsystem_nonconformity_repair/__init__.py
odoo/addons/mgmtsystem_nonconformity_repair/__manifest__.py
odoo/addons/mgmtsystem_nonconformity_repair/i18n/it.po
odoo/addons/mgmtsystem_nonconformity_repair/i18n/mgmtsystem_nonconformity_repair.pot
odoo/addons/mgmtsystem_nonconformity_repair/i18n/pt_BR.po
odoo/addons/mgmtsystem_nonconformity_repair/models/__init__.py
odoo/addons/mgmtsystem_nonconformity_repair/models/mgmtsystem_nonconformity.py
odoo/addons/mgmtsystem_nonconformity_repair/models/repair_order.py
odoo/addons/mgmtsystem_nonconformity_repair/readme/CONTRIBUTORS.rst
odoo/addons/mgmtsystem_nonconformity_repair/readme/DESCRIPTION.rst
odoo/addons/mgmtsystem_nonconformity_repair/readme/USAGE.rst
odoo/addons/mgmtsystem_nonconformity_repair/static/description/icon.png
odoo/addons/mgmtsystem_nonconformity_repair/static/description/index.html
odoo/addons/mgmtsystem_nonconformity_repair/views/mgmtsystem_nonconformity.xml
odoo12_addon_mgmtsystem_nonconformity_repair-12.0.1.0.0.99.dev8.dist-info/METADATA
odoo12_addon_mgmtsystem_nonconformity_repair-12.0.1.0.0.99.dev8.dist-info/WHEEL
odoo12_addon_mgmtsystem_nonconformity_repair-12.0.1.0.0.99.dev8.dist-info/top_level.txt
odoo12_addon_mgmtsystem_nonconformity_repair-12.0.1.0.0.99.dev8.dist-info/RECORD
